pingme-0.0.1.dist-info/entry_points.txt
pingme-0.0.1.dist-info/WHEEL
pingme-0.0.1.dist-info/DESCRIPTION.rst
pingme-0.0.1.dist-info/METADATA
pingme-0.0.1.dist-info/RECORD
pingme-0.0.1.dist-info/metadata.json
pingme-0.0.1.dist-info/top_level.txt
pingme/pingme.py
pingme/__init__.py
