Metadata-Version: 2.0
Name: pingme
Version: 0.0.1
Summary: Cli for Pingme Android application.
Home-page: https://github.com/teddy-schmitz/pingme-cli
Author: Teddy Schmitz
Author-email: lted.schmitz@gmail.com
License: UNKNOWN
Platform: UNKNOWN
Classifier: Development Status :: 1 - Planning
Classifier: Natural Language :: English
Classifier: Operating System :: OS Independent
Classifier: Programming Language :: Python :: 2.7
Requires-Dist: requests (==2.5.1)
Requires-Dist: mock (==1.0.1)
Requires-Dist: six
